{
  "gerado_em": "24/03/2026 11:51 UTC",
  "gerado_em_br": "24/03/2026 08:51",
  "anp": {
    "semana_referencia": "16/03/2026 a 22/03/2026",
    "preco_atual": 7.35,
    "semanas": [
      {
        "ini": "2026-01-05",
        "fim": "2026-01-11",
        "ini_br": "05/01",
        "fim_br": "11/01/2026",
        "label": "Jan/26",
        "preco": 6.08
      },
      {
        "ini": "2026-01-12",
        "fim": "2026-01-18",
        "ini_br": "12/01",
        "fim_br": "18/01/2026",
        "label": "Jan/26",
        "preco": 6.082
      },
      {
        "ini": "2026-01-19",
        "fim": "2026-01-25",
        "ini_br": "19/01",
        "fim_br": "25/01/2026",
        "label": "Jan/26",
        "preco": 6.084
      },
      {
        "ini": "2026-01-26",
        "fim": "2026-02-01",
        "ini_br": "26/01",
        "fim_br": "01/02/2026",
        "label": "Fev/26",
        "preco": 6.086
      },
      {
        "ini": "2026-02-02",
        "fim": "2026-02-08",
        "ini_br": "02/02",
        "fim_br": "08/02/2026",
        "label": "Fev/26",
        "preco": 6.09
      },
      {
        "ini": "2026-02-09",
        "fim": "2026-02-15",
        "ini_br": "09/02",
        "fim_br": "15/02/2026",
        "label": "Fev/26",
        "preco": 6.095
      },
      {
        "ini": "2026-02-16",
        "fim": "2026-02-22",
        "ini_br": "16/02",
        "fim_br": "22/02/2026",
        "label": "Fev/26",
        "preco": 6.1
      },
      {
        "ini": "2026-03-01",
        "fim": "2026-03-07",
        "ini_br": "01/03",
        "fim_br": "07/03/2026",
        "label": "Mar/26",
        "preco": 6.15
      },
      {
        "ini": "2026-03-08",
        "fim": "2026-03-14",
        "ini_br": "08/03",
        "fim_br": "14/03/2026",
        "label": "Mar/26",
        "preco": 6.89
      }
    ],
    "regioes": [
      {
        "nome": "Norte",
        "emoji": "🟢",
        "preco": 7.2
      },
      {
        "nome": "Nordeste",
        "emoji": "🟡",
        "preco": 7.07
      },
      {
        "nome": "Centro-Oeste",
        "emoji": "🟠",
        "preco": 6.85
      },
      {
        "nome": "Sudeste",
        "emoji": "🔵",
        "preco": 6.76
      },
      {
        "nome": "Sul",
        "emoji": "⚪",
        "preco": 6.668
      }
    ],
    "atualizado": "fallback — 14/03/2026"
  },
  "ipca": {
    "series": [
      {
        "label": "Dez/24",
        "valor": 0.52
      },
      {
        "label": "Jan/25",
        "valor": 0.16
      },
      {
        "label": "Fev/25",
        "valor": 1.31
      },
      {
        "label": "Mar/25",
        "valor": 0.56
      },
      {
        "label": "Abr/25",
        "valor": 0.43
      },
      {
        "label": "Mai/25",
        "valor": 0.26
      },
      {
        "label": "Jun/25",
        "valor": 0.24
      },
      {
        "label": "Jul/25",
        "valor": 0.26
      },
      {
        "label": "Ago/25",
        "valor": -0.11
      },
      {
        "label": "Set/25",
        "valor": 0.48
      },
      {
        "label": "Out/25",
        "valor": 0.09
      },
      {
        "label": "Nov/25",
        "valor": 0.18
      },
      {
        "label": "Dez/25",
        "valor": 0.33
      },
      {
        "label": "Jan/26",
        "valor": 0.33
      },
      {
        "label": "Fev/26",
        "valor": 0.7
      }
    ],
    "ultimo": 0.7,
    "ultimo_label": "Fev/26",
    "acum12": 3.75
  },
  "igpm": {
    "series": [
      {
        "label": "Dez/24",
        "valor": 0.94
      },
      {
        "label": "Jan/25",
        "valor": 0.27
      },
      {
        "label": "Fev/25",
        "valor": 1.06
      },
      {
        "label": "Mar/25",
        "valor": -0.34
      },
      {
        "label": "Abr/25",
        "valor": 0.24
      },
      {
        "label": "Mai/25",
        "valor": -0.49
      },
      {
        "label": "Jun/25",
        "valor": -1.67
      },
      {
        "label": "Jul/25",
        "valor": -0.77
      },
      {
        "label": "Ago/25",
        "valor": 0.36
      },
      {
        "label": "Set/25",
        "valor": 0.42
      },
      {
        "label": "Out/25",
        "valor": -0.36
      },
      {
        "label": "Nov/25",
        "valor": 0.27
      },
      {
        "label": "Dez/25",
        "valor": -0.01
      },
      {
        "label": "Jan/26",
        "valor": 0.41
      },
      {
        "label": "Fev/26",
        "valor": -0.73
      }
    ],
    "ultimo": -0.73,
    "ultimo_label": "Fev/26",
    "acum12": -2.67
  },
  "selic": {
    "series": [
      {
        "label": "Mar/25",
        "valor": 13.25
      },
      {
        "label": "Abr/25",
        "valor": 13.25
      },
      {
        "label": "Mai/25",
        "valor": 13.75
      },
      {
        "label": "Jun/25",
        "valor": 13.75
      },
      {
        "label": "Jul/25",
        "valor": 14.25
      },
      {
        "label": "Ago/25",
        "valor": 14.25
      },
      {
        "label": "Set/25",
        "valor": 14.75
      },
      {
        "label": "Out/25",
        "valor": 14.75
      },
      {
        "label": "Nov/25",
        "valor": 14.75
      },
      {
        "label": "Dez/25",
        "valor": 14.75
      },
      {
        "label": "Jan/26",
        "valor": 14.75
      },
      {
        "label": "Fev/26",
        "valor": 14.75
      }
    ],
    "atual": 14.75,
    "ultimo_label": "Fev/26"
  },
  "usd_brl": {
    "series": [],
    "atual": 5.2585
  },
  "inctl": {
    "ultimo": 0.22,
    "series": [
      {
        "label": "Mar/25",
        "valor": 0.32
      },
      {
        "label": "Abr/25",
        "valor": 0.4
      },
      {
        "label": "Mai/25",
        "valor": 0.35
      },
      {
        "label": "Jun/25",
        "valor": 0.18
      },
      {
        "label": "Jul/25",
        "valor": 0.25
      },
      {
        "label": "Ago/25",
        "valor": 0.05
      },
      {
        "label": "Set/25",
        "valor": 0.3
      },
      {
        "label": "Out/25",
        "valor": 0.45
      },
      {
        "label": "Nov/25",
        "valor": 0.32
      },
      {
        "label": "Dez/25",
        "valor": 0.38
      },
      {
        "label": "Jan/26",
        "valor": 0.28
      },
      {
        "label": "Fev/26",
        "valor": 0.55
      }
    ],
    "fonte": "CNT",
    "atualizado": "24/03/2026"
  },
  "noticias": [
    {
      "titulo": "'Brasil tem uma arma secreta contra crises do petróleo', diz The Economist",
      "link": "https://g1.globo.com/economia/noticia/2026/03/26/brasil-tem-uma-arma-secreta-contra-crises-do-petroleo-diz-the-economist.ghtml",
      "data": "26/03/2026",
      "fonte": "G1",
      "prioridade": 1,
      "imagem": "https://s2-g1.glbimg.com/0DF8JvbZYk2dFXopn_3FZQ5R65w=/1280x0/filters:format(jpeg)/https://thumbor.globoi.com/unsafe/fit-in/1280x720/s04.video.glbimg.com/deo/vi/55/20/992055"
    },
    {
      "titulo": "Sem o Estreito de Ormuz, Brasil fecha acordo com Turquia para rota alternativa para exportações do agronegócio",
      "link": "https://g1.globo.com/economia/agronegocios/noticia/2026/03/26/sem-o-estreito-de-ormuz-brasil-fecha-acordo-com-turquia-para-rota-alternativa-para-exportacoes.ghtml",
      "data": "26/03/2026",
      "fonte": "G1",
      "prioridade": 1,
      "imagem": "https://s2-g1.glbimg.com/PmE7zZbV6EzlPKwx4iJGH3EFxQs=/1200x0/filters:format(jpeg)/https://i.s3.glbimg.com/v1/AUTH_59edd422c0c84a879bd37670ae4f538a/internal_photos/bs/2025/u/g/dF3xXmTzqvEY1y51p6tw/conteiner-embarque-cafe.jpg"
    },
    {
      "titulo": "Como bloqueio de Ormuz tem sido lucrativo para o Irã",
      "link": "https://g1.globo.com/economia/noticia/2026/03/26/como-bloqueio-de-ormuz-tem-sido-lucrativo-para-o-ira.ghtml",
      "data": "26/03/2026",
      "fonte": "G1",
      "prioridade": 1,
      "imagem": "https://s2-g1.glbimg.com/kOz984yBCA_mmdUWyPOacWJEGBI=/1200x0/filters:format(jpeg)/https://i.s3.glbimg.com/v1/AUTH_59edd422c0c84a879bd37670ae4f538a/internal_photos/bs/2026/R/g/ozGSh5QOKlGlSPG6ruvQ/76389522-1004.webp"
    },
    {
      "titulo": "Qual o impacto de condenação nos EUA para o futuro das big techs? 'Um divisor de águas para as redes sociais'",
      "link": "https://g1.globo.com/tecnologia/noticia/2026/03/26/qual-o-impacto-de-condenacao-nos-eua-para-o-futuro-das-big-techs-um-divisor-de-aguas-para-as-redes-sociais.ghtml",
      "data": "26/03/2026",
      "fonte": "G1",
      "prioridade": 1,
      "imagem": "https://s2-g1.glbimg.com/YlwuPxPGUuifAsCu-IrWS4ciAhg=/1280x0/filters:format(jpeg)/https://s04.video.glbimg.com/x720/992055.jpg"
    },
    {
      "titulo": "Petrobras aumenta oferta de gasolina e diesel após alerta de risco de desabastecimento",
      "link": "https://g1.globo.com/economia/noticia/2026/03/26/petrobras-gasolina-diesel.ghtml",
      "data": "26/03/2026",
      "fonte": "G1",
      "prioridade": 1,
      "imagem": "https://s2-g1.glbimg.com/OtowCRweQWa1NIh79OMXOXjfDZs=/5472x0/filters:format(jpeg)/https://i.s3.glbimg.com/v1/AUTH_59edd422c0c84a879bd37670ae4f538a/internal_photos/bs/2026/p/w/wCR8ddTkWlDT6bfcazyg/mg-1446-0.jpg"
    },
    {
      "titulo": "IPCA-15: preços sobem 0,44% em março, bem acima das expectativas",
      "link": "https://g1.globo.com/economia/noticia/2026/03/26/ipca-15.ghtml",
      "data": "26/03/2026",
      "fonte": "G1",
      "prioridade": 1,
      "imagem": "https://s2-g1.glbimg.com/mNCDRUbghXHJhq6aevaWUV2L290=/2000x0/filters:format(jpeg)/https://i.s3.glbimg.com/v1/AUTH_59edd422c0c84a879bd37670ae4f538a/internal_photos/bs/2024/a/X/RNZw6lR3KkwZZzDa1DPQ/ato20231117089.jpg"
    },
    {
      "titulo": "Petrobras faz nova descoberta de petróleo em Marlim Sul, no pré-sal da Bacia de Campos",
      "link": "https://g1.globo.com/economia/noticia/2026/03/26/petrobras-faz-nova-descoberta-de-petroleo-em-marlim-sul-no-pre-sal-da-bacia-de-campos.ghtml",
      "data": "26/03/2026",
      "fonte": "G1",
      "prioridade": 1,
      "imagem": "https://s2-g1.glbimg.com/ULoZsszj5GS7tJkWVyaHxKj-ig0=/3252x0/filters:format(jpeg)/https://i.s3.glbimg.com/v1/AUTH_59edd422c0c84a879bd37670ae4f538a/internal_photos/bs/2026/k/7/HZspNFQYS2l0SquLHT0g/2026-02-10t231051z-1-lynxmpem191lg-rtroptp-4-brazil.jpg"
    },
    {
      "titulo": "Governo zera imposto de importação de quase mil produtos sem produção nacional ou com oferta insuficiente",
      "link": "https://g1.globo.com/economia/noticia/2026/03/26/governo-zera-imposto-de-importacao-de-quase-mil-produtos-sem-producao-nacional-ou-com-oferta-insuficiente.ghtml",
      "data": "26/03/2026",
      "fonte": "G1",
      "prioridade": 1,
      "imagem": "https://s2-g1.glbimg.com/xexjSOT3F2jEkI6Jll15xY1iqZc=/3840x0/filters:format(jpeg)/https://i.s3.glbimg.com/v1/AUTH_59edd422c0c84a879bd37670ae4f538a/internal_photos/bs/2025/X/I/8uRAvMQVCFcEULFZdWPw/sor-colheita-lupulo-260425-frame-3469.jpeg"
    },
    {
      "titulo": "Juiz do DF acata recurso de Nikolas Ferreira e anula indenização por discurso sobre pessoas trans",
      "link": "https://g1.globo.com/df/distrito-federal/noticia/2026/03/26/juiz-do-df-acata-recurso-de-nikolas-ferreira-e-anula-indenizacao-por-fala-em-plenario-sobre-pessoas-trans.ghtml",
      "data": "26/03/2026",
      "fonte": "G1",
      "prioridade": 1,
      "imagem": "https://s2-g1.glbimg.com/nU3qv_33f0Wpf1ychwl7h2bP0yM=/1280x0/filters:format(jpeg)/https://i.s3.glbimg.com/v1/AUTH_59edd422c0c84a879bd37670ae4f538a/internal_photos/bs/2023/9/y/i2Z3OESTaLKLXgbNBVAA/fotor-2023-3-21-18-44-18.jpg"
    },
    {
      "titulo": "Eduardo Leite afirma que Caiado é candidato de grupo que 'já tem representante' e se diz animado com possível candidatura à Presidência",
      "link": "https://g1.globo.com/rs/rio-grande-do-sul/eleicoes/2026/noticia/2026/03/26/leite-candidatura-presidente-kassab-reuniao.ghtml",
      "data": "26/03/2026",
      "fonte": "G1",
      "prioridade": 1,
      "imagem": "https://s2-g1.glbimg.com/4S3sd57Tgc19nSWCimjdvr9hHzY=/1600x0/filters:format(jpeg)/https://i.s3.glbimg.com/v1/AUTH_59edd422c0c84a879bd37670ae4f538a/internal_photos/bs/2026/q/3/PFCbXcSLisel88Rjn5dw/kassab-e-eduardo-leite.jpg"
    },
    {
      "titulo": "Câmara aprova MP que reajusta salário de polícia e bombeiros do DF",
      "link": "https://g1.globo.com/politica/noticia/2026/03/26/camara-aprova-mp-que-reajusta-salario-de-policia-e-bombeiros-do-df.ghtml",
      "data": "26/03/2026",
      "fonte": "G1",
      "prioridade": 1,
      "imagem": "https://s2-g1.glbimg.com/_fjjRc7ggBACSesbfzGpJAC1a9I=/2560x0/filters:format(jpeg)/https://i.s3.glbimg.com/v1/AUTH_59edd422c0c84a879bd37670ae4f538a/internal_photos/bs/2024/1/B/BEOM6STSWSBt0942A70g/cfp-edital-destaque-scaled.jpg"
    },
    {
      "titulo": "Cidadania italiana de Zambelli não impede extradição, aponta Justiça da Itália",
      "link": "https://g1.globo.com/mundo/noticia/2026/03/26/cidadania-italiana-de-zambelli-nao-impede-extradicao-aponta-justica-da-italia.ghtml",
      "data": "26/03/2026",
      "fonte": "G1",
      "prioridade": 1,
      "imagem": "https://s2-g1.glbimg.com/WLZItNxjGXSrpVOG3GYnAEhnDMY=/2121x0/filters:format(jpeg)/https://i.s3.glbimg.com/v1/AUTH_59edd422c0c84a879bd37670ae4f538a/internal_photos/bs/2025/v/J/qTks1vRiSJPROHruP2bg/ato20250515060.jpg"
    },
    {
      "titulo": "Ministra Sônia Guajajara recebe alta do InCor após cinco dias de internação",
      "link": "https://g1.globo.com/sp/sao-paulo/noticia/2026/03/26/ministra-sonia-guajajara-recebe-alta-do-incor-apos-cinco-dias-de-internacao.ghtml",
      "data": "26/03/2026",
      "fonte": "G1",
      "prioridade": 1,
      "imagem": "https://s2-g1.glbimg.com/RwCIc6gWSMlnl1RfKOD65pio8IM=/3342x0/filters:format(jpeg)/https://i.s3.glbimg.com/v1/AUTH_59edd422c0c84a879bd37670ae4f538a/internal_photos/bs/2026/9/H/JDVXjrQUKsl6NmLBGzNQ/0d4a5774.jpg"
    },
    {
      "titulo": "Defesa de Carla Zambelli recorre ao pedido de extradição na Itália; o que acontece agora?",
      "link": "https://g1.globo.com/mundo/noticia/2026/03/26/defesa-de-carla-zambelli-recorre-ao-pedido-de-extradicao-na-italia-o-que-acontece-agora.ghtml",
      "data": "26/03/2026",
      "fonte": "G1",
      "prioridade": 1,
      "imagem": "https://s2-g1.glbimg.com/BNj_Vxs6fKVx_vZk2hp0a7zgAwo=/1280x0/filters:format(jpeg)/https://s01.video.glbimg.com/x720/14467504.jpg"
    },
    {
      "titulo": "Lula cita elevação de gastos com cães no Brasil e diz que chineses não devem ter 'esse problema'",
      "link": "https://g1.globo.com/politica/noticia/2026/03/26/lula-cita-elevacao-de-gastos-com-cachorros-no-brasil-e-diz-que-chineses-nao-devem-ter-esse-tipo-de-problema.ghtml",
      "data": "26/03/2026",
      "fonte": "G1",
      "prioridade": 1,
      "imagem": ""
    },
    {
      "titulo": "Aneel reverte liminar da Light e restabelece reajuste tarifário menor para 2026",
      "link": "https://redir.folha.com.br/redir/online/mercado/rss091/*https://www1.folha.uol.com.br/mercado/2026/03/aneel-reverte-liminar-da-light-e-restabelece-reajuste-tarifario-menor-para-2026.shtml",
      "data": "26/03/2026",
      "fonte": "Folha SP",
      "prioridade": 1,
      "imagem": "https://f.i.uol.com.br/fotografia/2025/07/31/1753998598688be50620891_1753998598_3x2_rt.jpg"
    },
    {
      "titulo": "Após PM retirar alunos da Secretaria de Educação, manifestantes fazem novo protesto em SP",
      "link": "https://redir.folha.com.br/redir/online/cotidiano/rss091/*https://www1.folha.uol.com.br/educacao/2026/03/apos-pm-retirar-alunos-da-secretaria-de-educacao-manifestantes-fazem-novo-protesto-em-sp.shtml",
      "data": "26/03/2026",
      "fonte": "Folha SP",
      "prioridade": 1,
      "imagem": "https://f.i.uol.com.br/fotografia/2026/03/26/177453874969c54ffdb669d_1774538749_3x2_rt.jpg"
    },
    {
      "titulo": "Prédio na zona leste de SP é interditado após incêndio e gera protesto de moradores",
      "link": "https://redir.folha.com.br/redir/online/cotidiano/rss091/*https://www1.folha.uol.com.br/cotidiano/2026/03/predio-na-zona-leste-de-sp-e-interditado-pela-segunda-vez-apos-incendio-e-gera-protesto-de-moradores.shtml",
      "data": "26/03/2026",
      "fonte": "Folha SP",
      "prioridade": 1,
      "imagem": "https://f.i.uol.com.br/fotografia/2026/03/25/177447282969c44e7da183e_1774472829_3x2_lg.jpg"
    },
    {
      "titulo": "PM retira estudantes à força da Secretaria de Educação de SP durante a madrugada",
      "link": "https://redir.folha.com.br/redir/online/cotidiano/rss091/*https://www1.folha.uol.com.br/educacao/2026/03/pm-retira-estudantes-a-forca-da-secretaria-de-educacao-de-sp-durante-a-madrugada.shtml",
      "data": "26/03/2026",
      "fonte": "Folha SP",
      "prioridade": 1,
      "imagem": "https://f.i.uol.com.br/fotografia/2026/03/25/177448070269c46d3e1eebb_1774480702_3x2_lg.jpg"
    },
    {
      "titulo": "Combustível: Goldman espera distribuidoras com margens mais altas na 1ª metade do ano",
      "link": "https://www.infomoney.com.br/mercados/combustivel-goldman-espera-distribuidoras-com-margens-mais-altas-na-1a-metade-do-ano/",
      "data": "26/03/2026",
      "fonte": "InfoMoney",
      "prioridade": 1,
      "imagem": "https://www.infomoney.com.br/wp-content/uploads/2025/07/ipiranga-empresas-capa-ultrapar.webp?quality=70"
    },
    {
      "titulo": "UBS BB assume que Petrobras (PETR4) elevará preços no 2T26 e reforça recomendação de compra",
      "link": "https://www.moneytimes.com.br/ubs-bb-assume-que-petrobras-petr4-elevara-precos-no-2t26-e-reforca-recomendacao-de-compra-pads/",
      "data": "26/03/2026",
      "fonte": "Money Times",
      "prioridade": 1,
      "imagem": "https://www.moneytimes.com.br/uploads/2025/10/tanque-de-diesel-r5-na-rpbc-petrobras.jpg"
    },
    {
      "titulo": "Quem é Rafael Góis, CEO da Fictor e alvo de operação da PF por fraudes bancárias",
      "link": "https://g1.globo.com/economia/negocios/noticia/2026/03/25/quem-e-rafael-gois-ceo-da-fictor-e-alvo-de-operacao-da-pf-por-fraudes-bancarias.ghtml",
      "data": "25/03/2026",
      "fonte": "G1",
      "prioridade": 1,
      "imagem": "https://s2-g1.glbimg.com/kS8nbbioogeR-BiFJFLjZOxB9vI=/1297x0/filters:format(jpeg)/https://i.s3.glbimg.com/v1/AUTH_59edd422c0c84a879bd37670ae4f538a/internal_photos/bs/2026/3/q/Ohg9y7T9qnOG9eV9k8pA/1703684392766.jpg"
    },
    {
      "titulo": "Petrobras discutirá parceria em águas profundas com estatal mexicana Pemex",
      "link": "https://g1.globo.com/economia/noticia/2026/03/24/petrobras-parceria-estatal-mexicana-pemex.ghtml",
      "data": "25/03/2026",
      "fonte": "G1",
      "prioridade": 1,
      "imagem": "https://s2-g1.glbimg.com/OtowCRweQWa1NIh79OMXOXjfDZs=/5472x0/filters:format(jpeg)/https://i.s3.glbimg.com/v1/AUTH_59edd422c0c84a879bd37670ae4f538a/internal_photos/bs/2026/p/w/wCR8ddTkWlDT6bfcazyg/mg-1446-0.jpg"
    },
    {
      "titulo": "Loga vai testar caminhão VW Constellation a gás na coleta de lixo em SP",
      "link": "https://www.transportabrasil.com.br/2026/03/loga-vai-testar-caminhao-vw-constellation-a-gas-na-coleta-de-lixo-em-sp/",
      "data": "24/03/2026",
      "fonte": "Transporta Brasil",
      "prioridade": 1,
      "imagem": "https://www.transportabrasil.com.br/wp-content/uploads/2026/03/vw-biometano-loga.jpg"
    },
    {
      "titulo": "Falha em versões antigas do iPhone pode permitir espionagem e roubo de dados",
      "link": "https://g1.globo.com/tecnologia/noticia/2026/03/23/falha-em-versoes-antigas-do-iphone-pode-permitir-espionagem-e-roubo-de-dados.ghtml",
      "data": "23/03/2026",
      "fonte": "G1",
      "prioridade": 1,
      "imagem": "https://s2-g1.glbimg.com/ed10bo8p9XqOJVbdm1t76fvobtk=/1200x0/filters:format(jpeg)/https://i.s3.glbimg.com/v1/AUTH_59edd422c0c84a879bd37670ae4f538a/internal_photos/bs/2025/h/4/qECr9qTuSBmlmjBaz0Ag/afp-20250909-73xq6fg-v1-midres-appleexpectedtounveilanewiphonemodelataneventstr.jpg"
    },
    {
      "titulo": "Foton lança sete modelos elétricos para o transporte leve",
      "link": "https://www.transportabrasil.com.br/2026/03/foton-lanca-sete-modelos-eletricos-para-o-transporte-leve/",
      "data": "23/03/2026",
      "fonte": "Transporta Brasil",
      "prioridade": 1,
      "imagem": "https://www.transportabrasil.com.br/wp-content/uploads/2026/03/0b-Portfolio-Foton-Eletricos.jpg"
    },
    {
      "titulo": "Caminhões Hyundai Xcient movidos a célula de combustível chegam ao Uruguai",
      "link": "https://www.transportabrasil.com.br/2026/03/caminhoes-hyundai-xcient-movidos-a-celula-de-combustivel-chegam-ao-uruguai/",
      "data": "20/03/2026",
      "fonte": "Transporta Brasil",
      "prioridade": 1,
      "imagem": "https://www.transportabrasil.com.br/wp-content/uploads/2026/03/xcient-uruguai00.jpg"
    },
    {
      "titulo": "Petrobras compra fatia da Petronas em Tartaruga Verde e Espadarte por US$ 450 milhões",
      "link": "https://g1.globo.com/economia/noticia/2026/03/16/petrobras-compra-fatia-da-petronas-em-tartaruga-verde-e-espadarte-por-us-450-milhoes.ghtml",
      "data": "17/03/2026",
      "fonte": "G1",
      "prioridade": 1,
      "imagem": "https://s2-g1.glbimg.com/OtowCRweQWa1NIh79OMXOXjfDZs=/5472x0/filters:format(jpeg)/https://i.s3.glbimg.com/v1/AUTH_59edd422c0c84a879bd37670ae4f538a/internal_photos/bs/2026/p/w/wCR8ddTkWlDT6bfcazyg/mg-1446-0.jpg"
    },
    {
      "titulo": "VW vai testar biodiesel puro em seus caminhões na soja e nas rodovias",
      "link": "https://www.transportabrasil.com.br/2026/03/vw-vai-testar-biodiesel-puro-em-seus-caminhoes-na-soja-e-nas-rodovias/",
      "data": "17/03/2026",
      "fonte": "Transporta Brasil",
      "prioridade": 1,
      "imagem": "https://www.transportabrasil.com.br/wp-content/uploads/2026/03/vw-amaggi-b100-1.jpg"
    },
    {
      "titulo": "Renner deixa de vender camiseta com frase 'Regret Nothing', ligada a discurso misógino",
      "link": "https://g1.globo.com/economia/negocios/noticia/2026/03/13/renner-camiseta-regret-nothing.ghtml",
      "data": "13/03/2026",
      "fonte": "G1",
      "prioridade": 1,
      "imagem": "https://s2-g1.glbimg.com/uwMDXUJL8dVr0JeC-L1sTAxeEI8=/1200x0/filters:format(jpeg)/https://i.s3.glbimg.com/v1/AUTH_59edd422c0c84a879bd37670ae4f538a/internal_photos/bs/2026/0/9/i9L3UdQrW4RBnnbu8hoQ/imagem-cortada-2026-03-09t130828.243.jpg"
    }
  ],
  "econ_noticias": [
    {
      "titulo": "Petróleo fecha em alta de 4% e Brent retoma nível de US$ 100 com diálogo de EUA-Irã",
      "link": "https://www.infomoney.com.br/mercados/petroleo-abertura-fechamento-ira-eua-2603202/",
      "data": "26/03/2026",
      "fonte": "InfoMoney",
      "prioridade": 1,
      "imagem": "https://www.infomoney.com.br/wp-content/uploads/2025/06/2025-06-16T200909Z_1_LYNXMPEL5F0YT_RTROPTP_4_OIL-OPEC.jpg?quality=70"
    },
    {
      "titulo": "Braskem deve ter “deterioração significativa” nos resultados do 4T, apontam analistas",
      "link": "https://www.infomoney.com.br/mercados/braskem-deve-ter-deterioracao-significativa-nos-resultados-do-4t-apontam-analistas/",
      "data": "26/03/2026",
      "fonte": "InfoMoney",
      "prioridade": 1,
      "imagem": "https://www.infomoney.com.br/wp-content/uploads/2022/10/unnamed-3.jpg?quality=70"
    },
    {
      "titulo": "Dívida pública federal cresce 2,3% em fevereiro e vai a R$ 8,9 tri",
      "link": "https://redir.folha.com.br/redir/online/mercado/rss091/*https://www1.folha.uol.com.br/mercado/2026/03/divida-publica-federal-cresce-23-em-fevereiro-e-vai-a-r-89-tri.shtml",
      "data": "26/03/2026",
      "fonte": "Folha SP",
      "prioridade": 1,
      "imagem": "https://f.i.uol.com.br/fotografia/2019/08/31/15672908775d6af5fd3d099_1567290877_3x2_rt.jpg"
    },
    {
      "titulo": "STF interrompe julgamento sobre imunidade do ITBI após pedido de Dino",
      "link": "https://redir.folha.com.br/redir/online/mercado/rss091/*https://www1.folha.uol.com.br/blogs/que-imposto-e-esse/2026/03/stf-interrompe-julgamento-sobre-imunidade-do-itbi-apos-pedido-de-dino.shtml",
      "data": "26/03/2026",
      "fonte": "Folha SP",
      "prioridade": 1,
      "imagem": "https://f.i.uol.com.br/fotografia/2026/02/02/17700604376980fa959c1c9_1770060437_3x2_rt.jpg"
    },
    {
      "titulo": "Galípolo diz que BC vive luto por suspeita contra servidores e que não há salvador da pátria no caso Master",
      "link": "https://redir.folha.com.br/redir/online/mercado/rss091/*https://www1.folha.uol.com.br/mercado/2026/03/galipolo-diz-que-bc-vive-luto-por-suspeita-contra-servidores-e-que-nao-ha-salvador-da-patria-no-caso-master.shtml",
      "data": "26/03/2026",
      "fonte": "Folha SP",
      "prioridade": 1,
      "imagem": "https://f.i.uol.com.br/fotografia/2026/03/26/177454049069c556ca1d525_1774540490_3x2_rt.jpg"
    },
    {
      "titulo": "Petróleo da Venezuela seduz o setor, mas incerteza freia o entusiasmo",
      "link": "https://redir.folha.com.br/redir/online/mercado/rss091/*https://www1.folha.uol.com.br/mercado/2026/03/petroleo-da-venezuela-seduz-o-setor-mas-incerteza-freia-o-entusiasmo.shtml",
      "data": "26/03/2026",
      "fonte": "Folha SP",
      "prioridade": 1,
      "imagem": "https://f.i.uol.com.br/fotografia/2026/03/26/177454806569c5746156f02_1774548065_3x2_rt.jpg"
    },
    {
      "titulo": "Ivan Gontijo vai para conselho do Bradesco e grupo segurador se divide em duas empresas",
      "link": "https://redir.folha.com.br/redir/online/mercado/rss091/*https://aovivo.folha.uol.com.br/mercado/2026/03/01/6441-dolar-empresas-e-bolsas-acompanhe-ao-vivo-o-mercado.shtml#post450462",
      "data": "26/03/2026",
      "fonte": "Folha SP",
      "prioridade": 1,
      "imagem": "https://f.i.uol.com.br/hunting/folha/1/common/logo-folha-facebook-share.jpg"
    },
    {
      "titulo": "Anvisa proíbe venda de lote do azeite de oliva da marca Royal",
      "link": "https://redir.folha.com.br/redir/online/mercado/rss091/*https://aovivo.folha.uol.com.br/mercado/2026/03/01/6441-dolar-empresas-e-bolsas-acompanhe-ao-vivo-o-mercado.shtml#post450461",
      "data": "26/03/2026",
      "fonte": "Folha SP",
      "prioridade": 1,
      "imagem": "https://f.i.uol.com.br/hunting/folha/1/common/logo-folha-facebook-share.jpg"
    },
    {
      "titulo": "Entenda os processos sobre vício em redes sociais que condenaram Meta e Google",
      "link": "https://redir.folha.com.br/redir/online/mercado/rss091/*https://www1.folha.uol.com.br/tec/2026/03/entenda-os-processos-sobre-vicio-em-redes-sociais-que-condenaram-meta-e-google.shtml",
      "data": "26/03/2026",
      "fonte": "Folha SP",
      "prioridade": 1,
      "imagem": "https://f.i.uol.com.br/fotografia/2026/03/26/177454347569c56273e0dd5_1774543475_3x2_rt.jpg"
    },
    {
      "titulo": "'Brasil tem uma arma secreta contra crises do petróleo', diz The Economist",
      "link": "https://g1.globo.com/economia/noticia/2026/03/26/brasil-tem-uma-arma-secreta-contra-crises-do-petroleo-diz-the-economist.ghtml",
      "data": "26/03/2026",
      "fonte": "G1",
      "prioridade": 1,
      "imagem": "https://s2-g1.glbimg.com/0DF8JvbZYk2dFXopn_3FZQ5R65w=/1280x0/filters:format(jpeg)/https://thumbor.globoi.com/unsafe/fit-in/1280x720/s04.video.glbimg.com/deo/vi/55/20/992055"
    },
    {
      "titulo": "Justiça dos EUA rejeita ação da X, de Elon Musk, contra suposto ‘boicote’ de grandes empresas",
      "link": "https://g1.globo.com/tecnologia/noticia/2026/03/26/justica-dos-eua-rejeita-acao-do-x-de-elon-musk-contra-anunciantes.ghtml",
      "data": "26/03/2026",
      "fonte": "G1",
      "prioridade": 1,
      "imagem": "https://s2-g1.glbimg.com/tjBy4Hel1jZ-RSc9h12l6h4QrUM=/7681x0/filters:format(jpeg)/https://i.s3.glbimg.com/v1/AUTH_59edd422c0c84a879bd37670ae4f538a/internal_photos/bs/2024/z/g/g3UWyFSfu5CBAp2JdFNQ/x-rede-social.jpg"
    },
    {
      "titulo": "Como bloqueio de Ormuz tem sido lucrativo para o Irã",
      "link": "https://g1.globo.com/economia/noticia/2026/03/26/como-bloqueio-de-ormuz-tem-sido-lucrativo-para-o-ira.ghtml",
      "data": "26/03/2026",
      "fonte": "G1",
      "prioridade": 1,
      "imagem": "https://s2-g1.glbimg.com/kOz984yBCA_mmdUWyPOacWJEGBI=/1200x0/filters:format(jpeg)/https://i.s3.glbimg.com/v1/AUTH_59edd422c0c84a879bd37670ae4f538a/internal_photos/bs/2026/R/g/ozGSh5QOKlGlSPG6ruvQ/76389522-1004.webp"
    },
    {
      "titulo": "Petrobras aumenta oferta de gasolina e diesel após alerta de risco de desabastecimento",
      "link": "https://g1.globo.com/economia/noticia/2026/03/26/petrobras-gasolina-diesel.ghtml",
      "data": "26/03/2026",
      "fonte": "G1",
      "prioridade": 1,
      "imagem": "https://s2-g1.glbimg.com/OtowCRweQWa1NIh79OMXOXjfDZs=/5472x0/filters:format(jpeg)/https://i.s3.glbimg.com/v1/AUTH_59edd422c0c84a879bd37670ae4f538a/internal_photos/bs/2026/p/w/wCR8ddTkWlDT6bfcazyg/mg-1446-0.jpg"
    },
    {
      "titulo": "101 milhões de pessoas têm cartão de crédito, que responde por boa parte do endividamento, diz presidente do BC",
      "link": "https://g1.globo.com/economia/noticia/2026/03/26/101-milhoes-de-pessoas-tem-dividas-no-cartao-de-credito-com-juros-acima-de-100percent-ao-ano-diz-presidente-do-bc.ghtml",
      "data": "26/03/2026",
      "fonte": "G1",
      "prioridade": 1,
      "imagem": "https://s2-g1.glbimg.com/BlQem-QRHFj0OsOISFaRAOvXuRs=/4200x0/filters:format(jpeg)/https://i.s3.glbimg.com/v1/AUTH_59edd422c0c84a879bd37670ae4f538a/internal_photos/bs/2023/N/F/k8KZo1SSSVfm3AsG1SBw/fta20230509164.jpg"
    },
    {
      "titulo": "Brasil prorroga emergência zoossanitária por gripe aviária",
      "link": "https://g1.globo.com/economia/agronegocios/noticia/2026/03/26/brasil-prorroga-emergencia-zoossanitaria-por-gripe-aviaria-de-forma-preventiva.ghtml",
      "data": "26/03/2026",
      "fonte": "G1",
      "prioridade": 1,
      "imagem": "https://s2-g1.glbimg.com/uDIoEB-3Yas8wac3u1QgyL8ux0U=/6000x0/filters:format(jpeg)/https://i.s3.glbimg.com/v1/AUTH_59edd422c0c84a879bd37670ae4f538a/internal_photos/bs/2026/P/F/KMrS0VReW6bRL0sGaIOg/2026-03-26t145219z-1-lynxmpem2p0zq-rtroptp-4-brazil-eggs-usa.jpg"
    },
    {
      "titulo": "Tarifas de Trump tiveram pouco impacto no PIB de 2025 mas aumentaram receita, mostra estudo acadêmico",
      "link": "https://g1.globo.com/economia/noticia/2026/03/26/tarifas-de-trump-tiveram-pouco-impacto-no-pib-de-2025-mas-aumentaram-receita-mostra-estudo-academico.ghtml",
      "data": "26/03/2026",
      "fonte": "G1",
      "prioridade": 1,
      "imagem": "https://s2-g1.glbimg.com/AYxV4FjJInXolDw4FC-jF8iOlsk=/5900x0/filters:format(jpeg)/https://i.s3.glbimg.com/v1/AUTH_59edd422c0c84a879bd37670ae4f538a/internal_photos/bs/2025/Q/a/BDHWbVQsybWMup20rLOg/2025-05-29t001308z-2015437500-rc2xpdau1x0b-rtrmadp-3-usa-trump-tariffs-lawsuit.jpg"
    },
    {
      "titulo": "Ucrânia vê área de milho estável, choque de fertilizantes pode ocorrer em 2027",
      "link": "https://www.moneytimes.com.br/ucrania-ve-area-de-milho-estavel-choque-de-fertilizantes-pode-ocorrer-em-2027-pads/",
      "data": "26/03/2026",
      "fonte": "Money Times",
      "prioridade": 1,
      "imagem": "https://www.moneytimes.com.br/uploads/2025/09/etanol-milho-cana-de-acucar.jpg"
    },
    {
      "titulo": "Acima dos US$ 100? Petróleo sobe 4% com dúvidas sobre cessar-fogo no Oriente Médio",
      "link": "https://www.moneytimes.com.br/acima-dos-us-100-petroleo-sobe-4-com-duvidas-sobre-cessar-fogo-no-oriente-medio/",
      "data": "26/03/2026",
      "fonte": "Money Times",
      "prioridade": 1,
      "imagem": "https://www.moneytimes.com.br/uploads/2025/07/petroleo.jpg"
    },
    {
      "titulo": "Auxílio-moradia, auxílio-panetone, auxílio-peru e até auxílio-iPhone: conheça alguns dos mais inusitados penduricalhos vetados pelo STF",
      "link": "https://www.moneytimes.com.br/auxilio-moradia-auxilio-panetone-auxilio-peru-e-ate-auxilio-iphone-conheca-penduricalhos-vetados-pelo-stf-jcav/",
      "data": "26/03/2026",
      "fonte": "Money Times",
      "prioridade": 1,
      "imagem": "https://www.moneytimes.com.br/uploads/2026/03/imposto-pet-taxa-2.jpg"
    },
    {
      "titulo": "Ouro tomba quase 4% com incertezas de negociações de paz no Oriente Médio",
      "link": "https://www.moneytimes.com.br/ouro-26-3-26-apsa/",
      "data": "26/03/2026",
      "fonte": "Money Times",
      "prioridade": 1,
      "imagem": "https://www.moneytimes.com.br/uploads/2025/12/prata-e-ouro.png"
    },
    {
      "titulo": "IR 2026: imóvel na planta precisa ser declarado no imposto de renda?",
      "link": "https://exame.com/invest/minhas-financas/ir-2026-imovel-na-planta-precisa-ser-declarado-no-imposto-de-renda/",
      "data": "2026-03-26",
      "fonte": "Exame",
      "prioridade": 1,
      "imagem": "https://classic.exame.com/wp-content/uploads/2026/03/thumb_final_whatsapp.jpg"
    }
  ],
  "noticias_em": "26/03/2026 19:57 UTC",
  "noticias_em_br": "26/03/2026 16:57",
  "indicadores_em": "24/03/2026 11:51 UTC",
  "indicadores_em_br": "24/03/2026 08:51"
}